easymysql/__init__.py
easymysql/mysql.py
easymysql-0.1.9.3.dist-info/licenses/LICENSE.txt
easymysql-0.1.9.3.dist-info/METADATA
easymysql-0.1.9.3.dist-info/WHEEL
easymysql-0.1.9.3.dist-info/top_level.txt
easymysql-0.1.9.3.dist-info/RECORD
