Metadata-Version: 2.4
Name: easymysql
Version: 0.1.9.3
Summary: Easy MySQL Manager
Home-page: https://github.com/alvarodeleon/easymysql
Download-URL: https://github.com/alvarodeleon/easymysql/tarball/0.1.9.3
Author: Alvaro De Leon
Author-email: deleon@adl.com.uy
Keywords: mysql,sql,query
License-File: LICENSE.txt
Requires-Dist: pymysql
Dynamic: author
Dynamic: author-email
Dynamic: download-url
Dynamic: home-page
Dynamic: keywords
Dynamic: license-file
Dynamic: requires-dist
Dynamic: summary
